unigradicon/__init__.py
unigradicon-1.0.4.dist-info/LICENSE
unigradicon-1.0.4.dist-info/METADATA
unigradicon-1.0.4.dist-info/WHEEL
unigradicon-1.0.4.dist-info/entry_points.txt
unigradicon-1.0.4.dist-info/top_level.txt
unigradicon-1.0.4.dist-info/RECORD
