Metadata-Version: 2.1
Name: unigradicon
Version: 1.0.4
Summary: a foundation model for medical image registration
Home-page: https://github.com/uncbiag/uniGradICON
Author: Lin Tian
Author-email: lintian@cs.unc.edu
Project-URL: Bug Tracker, https://github.com/uncbiag/uniGradICON
Classifier: Programming Language :: Python :: 3
Classifier: License :: OSI Approved :: MIT License
Classifier: Operating System :: POSIX :: Linux
Requires-Python: >=3.8
License-File: LICENSE
Requires-Dist: icon-registration>=1.1.6
